Metadata-Version: 1.1
Name: RILseq
Version: 0.82
Summary: Processing RILSeq experiments results
Home-page: http://github.com/asafpr/RILseq
Author: Asaf Peer
Author-email: asafpr@gmail.com
License: MIT
Platform: UNKNOWN
Classifier: Development Status :: 3 - Alpha
Classifier: License :: OSI Approved :: MIT License
Classifier: Programming Language :: Python :: 3.7
Classifier: Topic :: Scientific/Engineering :: Bio-Informatics
